{
  "stat": {
    "interact_with_crafting_table": 373,
    "open_barrel": 10,
    "bell_ring": 5,
    "leave_game": 53,
    "time_since_death": 15320,
    "damage_blocked_by_shield": 4925,
    "play_time": 5101770,
    "deaths": 9,
    "jump": 43648,
    "enchant_item": 34,
    "interact_with_furnace": 275,
    "traded_with_villager": 521,
    "interact_with_cartography_table": 2,
    "sleep_in_bed": 72,
    "damage_dealt": 170696,
    "interact_with_smoker": 1,
    "horse_one_cm": 1766,
    "interact_with_smithing_table": 2,
    "inspect_dropper": 5,
    "interact_with_anvil": 7,
    "inspect_hopper": 132,
    "sneak_time": 86615,
    "interact_with_lectern": 1,
    "interact_with_blast_furnace": 1,
    "total_world_time": 5101770,
    "interact_with_stonecutter": 9,
    "time_since_rest": 15340,
    "swim_one_cm": 354568,
    "fly_one_cm": 7665736,
    "open_chest": 1534,
    "fall_one_cm": 804622,
    "animals_bred": 228,
    "open_shulker_box": 179,
    "sprint_one_cm": 13051444,
    "drop": 432,
    "talked_to_villager": 488,
    "interact_with_brewingstand": 12,
    "walk_on_water_one_cm": 348445,
    "interact_with_loom": 4,
    "open_enderchest": 6,
    "crouch_one_cm": 302390,
    "mob_kills": 1491,
    "fill_cauldron": 4,
    "climb_one_cm": 100712,
    "walk_one_cm": 11077283,
    "walk_under_water_one_cm": 271367,
    "boat_one_cm": 3460590,
    "pot_flower": 2,
    "interact_with_grindstone": 2,
    "damage_absorbed": 19,
    "damage_taken": 19760,
    "minecart_one_cm": 376,
    "aviate_one_cm": 2227640
  }
}